<?xml version="1.0" encoding="UTF-8"?><database>
    <element label="Purchase Order Hardware Options" max_length="40" name="x_chfa_amps_purchase_order_hwr_opt" sizeclass="0" type="collection">
        <element label="Active" max_length="40" name="active" type="boolean"/>
        <element choice="1" label="Category" max_length="40" name="category" type="choice">
            <choice>
                <element inactive_on_update="false" label="KPS" sequence="0" value="KPS"/>
                <element inactive_on_update="false" label="Miscellaneous" sequence="0" value="Miscellaneous"/>
                <element inactive_on_update="false" label="POS and Peripherals" sequence="0" value="POS and Peripherals"/>
                <element inactive_on_update="false" label="Powervars" sequence="0" value="Powervars"/>
                <element inactive_on_update="false" label="Scanners" sequence="0" value="Scanners"/>
            </choice>
        </element>
        <element display="true" label="Hardware" max_length="40" name="hardware" type="string"/>
        <element label="Part Description" max_length="100" name="part_description" type="string"/>
        <element label="Unit Price" max_length="20" name="unit_price" type="currency"/>
    </element>
</database>
